{
	"configurations" : 
	[
		{
			"directories" : 
			[
				{
					"build" : ".",
					"jsonFile" : "directory-.-Debug-f5ebdc15457944623624.json",
					"minimumCMakeVersion" : 
					{
						"string" : "3.21"
					},
					"projectIndex" : 0,
					"source" : ".",
					"targetIndexes" : 
					[
						0,
						1,
						2
					]
				}
			],
			"name" : "Debug",
			"projects" : 
			[
				{
					"directoryIndexes" : 
					[
						0
					],
					"name" : "camel_can_module",
					"targetIndexes" : 
					[
						0,
						1,
						2
					]
				}
			],
			"targets" : 
			[
				{
					"directoryIndex" : 0,
					"id" : "test_basic_cpp::@6890427a1f51a3e7e1df",
					"jsonFile" : "target-test_basic_cpp-Debug-80ad81a548ea5d669bce.json",
					"name" : "test_basic_cpp",
					"projectIndex" : 0
				},
				{
					"directoryIndex" : 0,
					"id" : "test_motor_x6::@6890427a1f51a3e7e1df",
					"jsonFile" : "target-test_motor_x6-Debug-9b82e684c4d5798cfc71.json",
					"name" : "test_motor_x6",
					"projectIndex" : 0
				},
				{
					"directoryIndex" : 0,
					"id" : "test_motor_x8_pro::@6890427a1f51a3e7e1df",
					"jsonFile" : "target-test_motor_x8_pro-Debug-27d4322e6d168c37939f.json",
					"name" : "test_motor_x8_pro",
					"projectIndex" : 0
				}
			]
		}
	],
	"kind" : "codemodel",
	"paths" : 
	{
		"build" : "/home/jaehyung/camel-can-module/cmake-build-debug",
		"source" : "/home/jaehyung/camel-can-module"
	},
	"version" : 
	{
		"major" : 2,
		"minor" : 3
	}
}
